README.md
setup.py
HuobiPoolApi.egg-info/PKG-INFO
HuobiPoolApi.egg-info/SOURCES.txt
HuobiPoolApi.egg-info/dependency_links.txt
HuobiPoolApi.egg-info/requires.txt
HuobiPoolApi.egg-info/top_level.txt
huobi_api/__init__.py
huobi_api/api_client.py
huobi_api/check_response.py
huobi_api/client.py
huobi_api/exceptions.py
huobi_api/signing.py
huobi_api/api/__init__.py
huobi_api/api/account.py
huobi_api/api/market.py
huobi_api/api/reference.py
huobi_api/api/subuser.py
huobi_api/api/wallet.py
huobi_api/tests/__init__.py