Metadata-Version: 2.1
Name: HuobiPoolApi
Version: 0.0.6
Summary: Huobi Pool api lib for easy work with huobi
Home-page: https://github.com/inkviz96/huobi_api_python
Author: Inkviz96
Author-email: b-semen-b@mail.ru
License: MIT
Keywords: huobi api pool
Platform: UNKNOWN
Classifier: Programming Language :: Python :: 3.8
Classifier: License :: OSI Approved :: GNU General Public License v3 (GPLv3)
